<?xml version="1.0" encoding="utf-8"?>
<i>
	<chatserver>chat.bilibili.com</chatserver>
	<chatid>1472639089</chatid>
	<mission>0</mission>
	<maxlimit>500</maxlimit>
	<state>0</state>
	<real_name>0</real_name>
	<source>k-v</source>
	<d p="48.56000,1,25,16777215,1711162687,0,df9f9bae,1544103553193685248,10">忘不了，那曾依籍的绿意</d>
	<d p="17.58900,5,25,15138834,1710670908,0,1d11270,1539978208408141312,10">白头发的灵梦（幻视</d>
	<d p="40.49000,5,25,16777215,1711020259,0,ebf08aad,1542908777555391232,10">在地上残存着的最后的幻想</d>
	<d p="0.00000,5,25,15138834,1710662948,0,857a527d,1539911436774895616,10">还有高手</d>
	<d p="5.77700,1,18,16777215,1711292867,0,b5a9cc4b,1545195580924622336,9">紫：半开的第三只眼……从今往后你映入你眼中的世界到底是什么样的呢</d>
	<d p="24.91500,1,25,16777215,1710845328,0,36016313,1541441349256252928,9">博 丽 灵 梦</d>
	<d p="0.88900,4,25,6684825,1711020103,0,ebf08aad,1542907474309481472,9">紫：半开的第三只眼……从今往后你映入你眼中的世界到底是什么样的呢</d>
	<d p="14.67800,1,25,16777215,1710692624,0,8a3fa98e,1540160379664165376,8">现实也7年了啊……</d>
	<d p="48.55100,1,25,16777215,1710948140,0,cb283199,1542303802982635008,8">草，绀珠传一面道中曲曲名</d>
	<d p="55.56700,5,25,16777215,1711020317,0,ebf08aad,1542909266602674688,8">（最终回9/9缓慢制作中）</d>
	<d p="16.83200,4,25,6684825,1711020196,0,ebf08aad,1542908254299239424,8">紫：逃避现实的你，不顾一切地挣扎着面对现实。         我其实…挺高兴的</d>
	<d p="3.33900,1,25,16777215,1710663484,0,3d287da2,1539915937522774784,7">腹泻式更新啊</d>
	<d p="20.71400,5,25,16646914,1730271293,0,ec4264ea,1704398154218388224,7">巧了还真有个白发灵梦的同人stg，挺温馨的（</d>
	<d p="12.44100,1,25,16777215,1729934833,0,6f60cb3c,1701575723942799104,7">被撕碎的恋之瞳</d>
	<d p="24.09900,5,25,16777215,1723491355,0,5fedb826,1647523918480841472,6">不顾一切的逃避现实，面对现实吧</d>
	<d p="24.09900,5,25,16777215,1723491271,0,5fedb826,1647523211858311936,6">我只是觉得很冷</d>
	<d p="24.09900,5,25,16777215,1723491193,0,5fedb826,1647522557336870656,6">盲目的逃避现实，转来转去的你</d>
	<d p="53.36400,1,25,16777215,1718460537,0,2f190bda,1605322351539828480,6">这里是巧妙的双关</d>
	<d p="52.01700,1,25,16777215,1718460526,0,2f190bda,1605322261823342336,5">绿和紫的假名都可以是「ゆかり」</d>
	<d p="47.25400,5,25,16777215,1711020291,0,ebf08aad,1542909048549463040,5">难忘的翠绿</d>
	<d p="44.13400,4,25,16777215,1711020276,0,ebf08aad,1542908919221915392,5">新生代、第四纪大量灭绝</d>
	<d p="39.18700,4,25,16777215,1711020251,0,ebf08aad,1542908709012191232,4">（地球）轨道上静止了的月亮</d>
	<d p="27.34900,4,25,6684825,1711020220,0,ebf08aad,1542908450995261696,4">紫：可以的哦，去散步</d>
	<d p="4.17900,1,25,16777215,1710692432,0,9dbba042,1540158764748182016,4">啊</d>
	<d p="8.55000,1,25,16777215,1710670882,0,1d11270,1539977996780233216,4">看起来好痛...</d>
	<d p="0.00000,1,25,16777215,1710666006,0,efb5dbe4,1539937087770445824,3">什么腹泻式更新</d>
	<d p="8.87900,1,25,16777215,1710665244,0,5fda0cd2,1539930700894010112,3">啊？</d>
	<d p="8.31700,1,25,16777215,1710661155,0,947b707f,1539896394121524480,3">啊？</d>
	<d p="2.36500,1,25,16777215,1710659788,0,ce429320,1539884931902519808,2">啊？感觉一日一更还是保守了</d>
	<d p="56.71700,1,25,16777215,1710659175,0,11ba9e61,1539879791933951744,2">啊？</d>
	<d p="6.97200,1,25,16777215,1710657774,0,a8fa5cf0,1539868036918893056,2">量产啊！?</d>
	<d p="0.00000,1,25,16777215,1710656836,0,2e0f61c5,1539860170585564416,2">什么更新速度</d>
	<d p="0.47900,1,25,16777215,1710656775,0,10267834,1539859658687417088,1">啊？</d>
	<d p="3.42100,1,25,16777215,1710656724,0,6cd704b8,1539859225767902976,1">啊？</d>
	<d p="1.89500,1,25,16777215,1710656491,0,2181ae41,1539857271482730752,1">啊？</d>
</i>
