<?xml version="1.0" encoding="utf-8"?>
<i>
	<chatserver>chat.bilibili.com</chatserver>
	<chatid>1649272863</chatid>
	<mission>0</mission>
	<maxlimit>100</maxlimit>
	<state>0</state>
	<real_name>0</real_name>
	<source>k-v</source>
	<d p="4.88400,1,25,16777215,1724072660,0,72746107,1652400258137149952,10">我们的神子不是吗</d>
	<d p="0.40100,1,25,16777215,1725021931,0,228dfde8,1660363320492226816,10">魔理鲨</d>
	<d p="10.73100,4,25,16777215,1729935074,0,21a02d2a,1701577749615746560,10">没有爱丽丝？</d>
	<d p="0.65900,1,25,16777215,1737389180,0,4ff0e659,1764107323242216960,10">魔老虎</d>
	<d p="2.23800,1,25,16777215,1724468510,0,cb57de7d,1655720881768371968,9">有种饥荒模型的感觉</d>
	<d p="6.89900,1,25,16777215,1737050087,0,6677466b,1761262801189508608,9">接线少数。哈哈哈哈哈哈啊哈哈哈。</d>
	<d p="0.00000,1,25,16777215,1747548890,0,b1115664,1849333146559693312,9">绝区零的小曲</d>
	<d p="2.55900,1,25,16777215,1723693690,0,9b80cb3,1649221224653430272,3">麻恰</d>
	<d p="4.23900,5,25,15138834,1723782539,0,59de3c46,1649966540335964160,1">灵梦：立了</d>
	<d p="0.64400,1,25,16777215,1723828405,0,a2614e5a,1650351298555659776,1">幻想乡唯一男主</d>
	<d p="6.28600,5,25,6830715,1724235182,0,23cc5f54,1653763590479862528,1">帕秋莉：我也立了</d>
	<d p="2.21900,1,25,16777215,1724896677,0,226814c9,1659312607712371712,1">爱丽丝：立了</d>
	<d p="6.80300,5,25,15138834,1725015629,0,3d8fc01b,1660310453554938880,1">无鸡之谈↑</d>
	<d p="9.25800,5,25,16707842,1725180748,0,9b0c18e0,1661695575231567616,1">爱丽丝：一起立吧</d>
	<d p="8.21200,5,25,16777215,1725708907,0,1589783d,1666126087769604096,1">爱丽丝也干了</d>
	<d p="11.43900,5,25,16707842,1729401394,0,ee8af571,1697100917817555712,1">爱丽丝：我也立了</d>
	<d p="4.82200,1,25,16777215,1737389225,0,4ff0e659,1764107696803652864,1">来魔法之森,有你好果子吃</d>
</i>
